{"lastUsed":1539264650792,"path":"Z:\/JavaProject","projectCount":3,"recentFiles":[{"path":"\/02_MaxOfThree\/src\/maxofthree","parentWorkspace":"Z:\/JavaProject","name":"MaxOfThree.java","lastModified":1539262909888,"locationURI":"file:\/Z:\/JavaProject\/02_MaxOfThree\/src\/maxofthree\/MaxOfThree.java"},{"path":"\/03_QuadraticEquation\/src\/quadraticequasion","parentWorkspace":"Z:\/JavaProject","name":"QuadraticEquation.java","lastModified":1539264654734,"locationURI":"file:\/Z:\/JavaProject\/03_QuadraticEquation\/src\/quadraticequasion\/QuadraticEquation.java"},{"path":"\/01_Reading\/src\/reading","parentWorkspace":"Z:\/JavaProject","name":"Reading.java","lastModified":1539264654996}]}